sphinx_integral_theme/__init__.py
sphinx_integral_theme/breadcrumbs.html
sphinx_integral_theme/footer.html
sphinx_integral_theme/header.html
sphinx_integral_theme/layout.html
sphinx_integral_theme/localtoc.html
sphinx_integral_theme/relations.html
sphinx_integral_theme/searchbox.html
sphinx_integral_theme/sourcelink.html
sphinx_integral_theme/theme.conf
sphinx_integral_theme/static/favicon.svg
sphinx_integral_theme/static/scripts.js
sphinx_integral_theme/static/styles.css
sphinx_integral_theme-0.0.11.dist-info/entry_points.txt
sphinx_integral_theme-0.0.11.dist-info/WHEEL
sphinx_integral_theme-0.0.11.dist-info/METADATA
sphinx_integral_theme-0.0.11.dist-info/RECORD
