Metadata-Version: 2.1
Name: sphinx-integral-theme
Version: 0.0.11
Summary: Sphinx Integral theme
Keywords: sphinx,sphinx-doc,theme,thestageai
Author-email: Slava Zytsar <s.zytsar@thestage.ai>, Alexey Zauzin <a.zauzin@thestage.ai>
Requires-Python: >=3.7
Requires-Dist: importlib-metadata; python_version<"3.8"
